linux_clipboard_manager-1.1.3.dist-info/licenses/LICENSE
src/__init__.py
src/__main__.py
src/clipboard_monitor.py
src/config.py
src/content_analyzer.py
src/hotkey_handler.py
src/storage.py
src/ui.py
linux_clipboard_manager-1.1.3.dist-info/METADATA
linux_clipboard_manager-1.1.3.dist-info/WHEEL
linux_clipboard_manager-1.1.3.dist-info/entry_points.txt
linux_clipboard_manager-1.1.3.dist-info/top_level.txt
linux_clipboard_manager-1.1.3.dist-info/RECORD
