Metadata-Version: 2.4
Name: linux-clipboard-manager
Version: 1.1.3
Summary: A powerful clipboard manager with history, search, and smart categorization
Home-page: https://github.com/krakujs/linux-clipboard-manager
Author: Smart Clipboard Team
Author-email: contact@smart-clipboard.com
Project-URL: Bug Reports, https://github.com/krakujs/linux-clipboard-manager/issues
Project-URL: Source, https://github.com/krakujs/linux-clipboard-manager
Project-URL: Documentation, https://github.com/krakujs/linux-clipboard-manager/blob/main/README.md
Keywords: clipboard manager history copy paste productivity
Classifier: Development Status :: 4 - Beta
Classifier: Intended Audience :: End Users/Desktop
Classifier: Topic :: Utilities
Classifier: Topic :: Desktop Environment
Classifier: License :: OSI Approved :: MIT License
Classifier: Programming Language :: Python :: 3
Classifier: Programming Language :: Python :: 3.8
Classifier: Programming Language :: Python :: 3.9
Classifier: Programming Language :: Python :: 3.10
Classifier: Programming Language :: Python :: 3.11
Classifier: Programming Language :: Python :: 3.12
Classifier: Operating System :: POSIX :: Linux
Classifier: Operating System :: Microsoft :: Windows
Classifier: Operating System :: MacOS :: MacOS X
Requires-Python: >=3.8
License-File: LICENSE
Requires-Dist: pyperclip>=1.8.2
Requires-Dist: pynput>=1.7.6
Requires-Dist: pillow>=10.0.0
Requires-Dist: python-dateutil>=2.8.2
Requires-Dist: cryptography>=41.0.0
Requires-Dist: pytest>=7.4.0
Requires-Dist: pytest-cov>=4.1.0
Provides-Extra: dev
Requires-Dist: pytest>=7.4.0; extra == "dev"
Requires-Dist: pytest-cov>=4.1.0; extra == "dev"
Requires-Dist: flake8>=5.0.0; extra == "dev"
Requires-Dist: black>=22.0.0; extra == "dev"
Requires-Dist: isort>=5.10.0; extra == "dev"
Provides-Extra: windows
Requires-Dist: pywin32>=305; extra == "windows"
Requires-Dist: psutil>=5.9.0; extra == "windows"
Dynamic: author
Dynamic: author-email
Dynamic: classifier
Dynamic: description
Dynamic: description-content-type
Dynamic: home-page
Dynamic: keywords
Dynamic: license-file
Dynamic: project-url
Dynamic: provides-extra
Dynamic: requires-dist
Dynamic: requires-python
Dynamic: summary
